{
    "type":"",
    "user":{
       "id":"",
       "username":"",
       "name":"",
       "team_id":""
    },
    "api_app_id":"",
    "token":"",
    "container":{
       "type":"",
       "message_ts":"",
       "attachment_id":1,
       "channel_id":"",
       "is_ephemeral":false,
       "is_app_unfurl":false
    },
    "trigger_id":"",
    "team":{
       "id":"",
       "domain":""
    },
    "enterprise":null,
    "is_enterprise_install":false,
    "channel":{
       "id":"",
       "name":""
    },
    "message":{
       "type":"",
       "subtype":"",
       "text":"",
       "ts":"",
       "bot_id":"",
       "attachments":[
          {
             "id":1,
             "blocks":[
                {
                   "type":"",
                   "block_id":"",
                   "text":{
                      "type":"",
                      "text":"",
                      "verbatim":false
                   }
                },
                {
                   "type":"",
                   "block_id":"",
                   "fields":[
                      {
                         "type":"",
                         "text":"",
                         "verbatim":false
                      },
                      {
                         "type":"",
                         "text":"",
                         "verbatim":false
                      },
                      {
                         "type":"",
                         "text":"",
                         "verbatim":false
                      },
                      {
                         "type":"",
                         "text":"",
                         "verbatim":false
                      }
                   ]
                },
                {
                   "type":"",
                   "block_id":""
                },
                {
                   "type":"",
                   "block_id":"",
                   "fields":[
                      {
                         "type":"",
                         "text":"",
                         "verbatim":false
                      }
                   ]
                },
                {
                   "type":"",
                   "block_id":"",
                   "elements":[
                      {
                         "type":"",
                         "action_id":"",
                         "text":{
                            "type":"",
                            "text":"",
                            "emoji":true
                         },
                         "style":"",
                         "value":""
                      },
                      {
                         "type":"",
                         "action_id":"",
                         "text":{
                            "type":"",
                            "text":"",
                            "emoji":true
                         },
                         "style":"",
                         "value":""
                      }
                   ]
                }
             ],
             "color":"",
             "fallback":""
          }
       ]
    },
    "state":{
       "values":{
          
       }
    },
    "response_url":"",
    "actions":[
       {
          "action_id":"",
          "block_id":"",
          "text":{
             "type":"",
             "text":"",
             "emoji": true
          },
          "value":"",
          "style":"",
          "type":"",
          "action_ts":""
       }
    ]
 }